auto_preprocess/__init__.py
auto_preprocess/_base.py
auto_preprocess/_clippers.py
auto_preprocess/_function_transformers.py
auto_preprocess/_selectors.py
auto_preprocess/config.py
auto_preprocess/examples.py
auto_preprocess/pipeline.py
auto_preprocess/utils.py
auto_preprocess-0.0.1.dist-info/LICENSE
auto_preprocess-0.0.1.dist-info/METADATA
auto_preprocess-0.0.1.dist-info/WHEEL
auto_preprocess-0.0.1.dist-info/top_level.txt
auto_preprocess-0.0.1.dist-info/RECORD
