Metadata-Version: 2.1
Name: auto-preprocess
Version: 0.0.1
Summary: Auto PreProcess package
Author: Eduardo M. de Morais
Author-email: emdemor415@gmail.com
License: MIT License
License-File: LICENSE
Requires-Dist: category-encoders
Requires-Dist: numpy
Requires-Dist: optbinning
Requires-Dist: pandas
Requires-Dist: PyYAML
Requires-Dist: scikit-learn
Requires-Dist: sklearn-pandas
Requires-Dist: tqdm
